<?xml version="1.0" encoding="utf-8" ?><dwsync><file name="readme.txt" server="eddie-brock.dreamhost.com/brethummel.com/clients/starter/dev/wp-content/themes/theme/" local="3719329697" remote="3728161080" Dst="-1" /><file name="block_legal.php" server="eddie-brock.dreamhost.com/brethummel.com/clients/starter/dev/wp-content/themes/theme/" local="3719619896" remote="3728161080" Dst="-1" /><file name="block_legal.js" server="eddie-brock.dreamhost.com/brethummel.com/clients/starter/dev/wp-content/themes/theme/" local="3719329697" remote="3728161080" Dst="-1" /><file name="block_legal.acf" server="eddie-brock.dreamhost.com/brethummel.com/clients/starter/dev/wp-content/themes/theme/" local="3722098377" remote="3728161080" Dst="-1" /><file name="acf-block_legal.json" server="eddie-brock.dreamhost.com/brethummel.com/clients/starter/dev/wp-content/themes/theme/" local="3721579625" remote="3728161080" Dst="-1" /><file name="_block_legal.scss" server="eddie-brock.dreamhost.com/brethummel.com/clients/starter/dev/wp-content/themes/theme/" local="3719329697" remote="3728161080" Dst="-1" /><file name="block_legal.php" server="eddie-brock.dreamhost.com/brethummel.com/clients/sus/sus016/dev/wp-content/themes/tursso/" local="3719619896" remote="3719612640" Dst="-1" /><file name="acf-block_legal.json" server="eddie-brock.dreamhost.com/alomere/wp-content/themes/alomere/" local="3719329697" remote="3719620377" Dst="-1" /><file name="_block_legal.scss" server="eddie-brock.dreamhost.com/alomere/wp-content/themes/alomere/" local="3719329697" remote="3719620377" Dst="-1" /><file name="block_legal.js" server="eddie-brock.dreamhost.com/alomere/wp-content/themes/alomere/" local="3719329697" remote="3719620378" Dst="-1" /><file name="readme.txt" server="eddie-brock.dreamhost.com/alomere/wp-content/themes/alomere/" local="3719329697" remote="3719620378" Dst="-1" /><file name="block_legal.acf" server="eddie-brock.dreamhost.com/alomere/wp-content/themes/alomere/" local="3719329698" remote="3719620378" Dst="-1" /><file name="block_legal.php" server="eddie-brock.dreamhost.com/alomere/wp-content/themes/alomere/" local="3719619896" remote="3719620378" Dst="-1" /><file name="acf-block_legal.json" server="eddie-brock.dreamhost.com/brethummel.com/clients/spr/spr001/dev/wp-content/themes/springboard/" local="3755262924" remote="3766330453" Dst="-1" /><file name="_block_legal.scss" server="eddie-brock.dreamhost.com/brethummel.com/clients/spr/spr001/dev/wp-content/themes/springboard/" local="3719329697" remote="3766328734" Dst="-1" /><file name="block_legal.js" server="eddie-brock.dreamhost.com/brethummel.com/clients/spr/spr001/dev/wp-content/themes/springboard/" local="3719329697" remote="3766328734" Dst="-1" /><file name="readme.txt" server="eddie-brock.dreamhost.com/brethummel.com/clients/spr/spr001/dev/wp-content/themes/springboard/" local="3719329697" remote="3766328735" Dst="-1" /><file name="block_legal.acf" server="eddie-brock.dreamhost.com/brethummel.com/clients/spr/spr001/dev/wp-content/themes/springboard/" local="3755309018" remote="3766330453" Dst="-1" /><file name="block_legal.php" server="eddie-brock.dreamhost.com/brethummel.com/clients/spr/spr001/dev/wp-content/themes/springboard/" local="3755262927" remote="3766330454" Dst="-1" /><file name="acf-block_legal.json" server="eddie-brock.dreamhost.com/brethummel.com/clients/squ/squ001/dev/wp-content/themes/trident/" local="3721579625" remote="3750676680" Dst="-1" /><file name="_block_legal.scss" server="eddie-brock.dreamhost.com/brethummel.com/clients/squ/squ001/dev/wp-content/themes/trident/" local="3719329697" remote="3750676680" Dst="-1" /><file name="block_legal.js" server="eddie-brock.dreamhost.com/brethummel.com/clients/squ/squ001/dev/wp-content/themes/trident/" local="3719329697" remote="3750676680" Dst="-1" /><file name="readme.txt" server="eddie-brock.dreamhost.com/brethummel.com/clients/squ/squ001/dev/wp-content/themes/trident/" local="3719329697" remote="3750676680" Dst="-1" /><file name="block_legal.acf" server="eddie-brock.dreamhost.com/brethummel.com/clients/squ/squ001/dev/wp-content/themes/trident/" local="3751217168" remote="3751209960" Dst="-1" /><file name="block_legal.php" server="eddie-brock.dreamhost.com/brethummel.com/clients/squ/squ001/dev/wp-content/themes/trident/" local="3734816117" remote="3750676680" Dst="-1" /><file name="icon_legal.png" server="eddie-brock.dreamhost.com/brethummel.com/clients/spr/spr001/dev/wp-content/themes/springboard/" local="3755746446" remote="3766330453" Dst="-1" /><file name="_admin_legal.scss" server="eddie-brock.dreamhost.com/brethummel.com/clients/spr/spr001/dev/wp-content/themes/springboard/" local="3755743521" remote="3766330453" Dst="-1" /><file name="acf-block_legal.json" server="eddie-brock.dreamhost.com/cur008.brethummel.com/wp-content/themes/curious/" local="3755262924" remote="3785178285" Dst="-1" /><file name="_block_legal.scss" server="eddie-brock.dreamhost.com/cur008.brethummel.com/wp-content/themes/curious/" local="3719329697" remote="3785178285" Dst="-1" /><file name="icon_legal.png" server="eddie-brock.dreamhost.com/cur008.brethummel.com/wp-content/themes/curious/" local="3755746446" remote="3785178286" Dst="-1" /><file name="_admin_legal.scss" server="eddie-brock.dreamhost.com/cur008.brethummel.com/wp-content/themes/curious/" local="3755743521" remote="3785178286" Dst="-1" /><file name="block_legal.js" server="eddie-brock.dreamhost.com/cur008.brethummel.com/wp-content/themes/curious/" local="3719329697" remote="3785178286" Dst="-1" /><file name="readme.txt" server="eddie-brock.dreamhost.com/cur008.brethummel.com/wp-content/themes/curious/" local="3719329697" remote="3785178286" Dst="-1" /><file name="block_legal.acf" server="eddie-brock.dreamhost.com/cur008.brethummel.com/wp-content/themes/curious/" local="3755309018" remote="3785178287" Dst="-1" /><file name="block_legal.php" server="eddie-brock.dreamhost.com/cur008.brethummel.com/wp-content/themes/curious/" local="3755262927" remote="3785178287" Dst="-1" /></dwsync>